cyborg_scheduler/__init__.py
cyborg_scheduler/monitor.py
cyborg_scheduler/task_queue.py
cyborg_scheduler/token_bucket.py
cyborg_scheduler/backends/__init__.py
cyborg_scheduler/backends/base.py
cyborg_scheduler/backends/local.py
cyborg_scheduler/backends/redis.py
cyborg_scheduler-0.0.4.dev1.dist-info/DESCRIPTION.rst
cyborg_scheduler-0.0.4.dev1.dist-info/METADATA
cyborg_scheduler-0.0.4.dev1.dist-info/RECORD
cyborg_scheduler-0.0.4.dev1.dist-info/WHEEL
cyborg_scheduler-0.0.4.dev1.dist-info/metadata.json
cyborg_scheduler-0.0.4.dev1.dist-info/top_level.txt
