Metadata-Version: 2.0
Name: cyborg-scheduler
Version: 0.0.4.dev1
Summary: A task queue based on redis
Home-page: UNKNOWN
Author: Zhang Wei
Author-email: zhangwei@yimian.com.cn
License: MIT
Keywords: task queue python
Platform: UNKNOWN
Classifier: Intended Audience :: Developers
Classifier: License :: OSI Approved :: MIT License
Classifier: Programming Language :: Python :: 3.4
Classifier: Programming Language :: Python :: 3.5
Classifier: Programming Language :: Python :: 3.6
Requires-Python: >=3.4
Requires-Dist: hiredis (>=0.2.0)
Requires-Dist: pyee (>=3.0.3)
Requires-Dist: redis (>=2.10.5)
Requires-Dist: sortedcontainers (>=1.5.7)
Requires-Dist: tornado (>=4.5.1)
Requires-Dist: suitcase (>=0.10.2)
